hypersolver/__init__.py
hypersolver/derivative.py
hypersolver/lax_friedrichs.py
hypersolver/lax_wendroff.py
hypersolver/method_of_characteristics.py
hypersolver/runge_kutta.py
hypersolver/util.py
hypersolver/tests/derivative_test.py
hypersolver/tests/lax_friedrichs_test.py
hypersolver/tests/lax_wendroff_test.py
hypersolver/tests/method_of_characteristics_test.py
hypersolver/tests/runge_kutta_test.py
hypersolver/tests/util_test.py
hypersolver-0.0.8.dist-info/WHEEL
hypersolver-0.0.8.dist-info/METADATA
hypersolver-0.0.8.dist-info/RECORD
